telugu_engine/__init__.py
telugu_engine/choice.py
telugu_engine/cli.py
telugu_engine/combo_pipeline.py
telugu_engine/enhanced_telugu_mappings.py
telugu_engine/enhanced_tense.py
telugu_engine/fixed_combo_pipeline.py
telugu_engine/grammar.py
telugu_engine/improved_suggest.py
telugu_engine/merged_pipeline.py
telugu_engine/optimal_setup_py.py
telugu_engine/phonetic_matrix.py
telugu_engine/sandhi_aware_combiner.py
telugu_engine/suggest.py
telugu_engine/suggest_sentence.py
telugu_engine/transliterator.py
telugu_engine/transliterator_v4.3.0.py
telugu_engine/v3_validator.py
telugu_language_tools-6.2.1.dist-info/licenses/LICENSE
telugu_language_tools-6.2.1.dist-info/METADATA
telugu_language_tools-6.2.1.dist-info/WHEEL
telugu_language_tools-6.2.1.dist-info/entry_points.txt
telugu_language_tools-6.2.1.dist-info/top_level.txt
telugu_language_tools-6.2.1.dist-info/RECORD
