Metadata-Version: 2.4
Name: telugu-language-tools
Version: 6.2.1
Summary: Modern Telugu v3.0 compliant library with present continuous tense, modern pronouns, comprehensive validation, and 100% test coverage
Author-email: Telugu Library Contributors <support@telugulibrary.org>
License: MIT
Project-URL: Homepage, https://github.com/yourusername/telugu_lib
Project-URL: Repository, https://github.com/yourusername/telugu_lib
Project-URL: Issues, https://github.com/yourusername/telugu_lib/issues
Project-URL: Documentation, https://github.com/yourusername/telugu_lib/blob/main/README.md
Keywords: telugu,language,v3.0,transliteration,text-processing,nlp,modern-telugu
Classifier: Development Status :: 5 - Production/Stable
Classifier: Intended Audience :: Developers
Classifier: Intended Audience :: Science/Research
Classifier: License :: OSI Approved :: MIT License
Classifier: Programming Language :: Python :: 3
Classifier: Programming Language :: Python :: 3.7
Classifier: Programming Language :: Python :: 3.8
Classifier: Programming Language :: Python :: 3.9
Classifier: Programming Language :: Python :: 3.10
Classifier: Programming Language :: Python :: 3.11
Classifier: Programming Language :: Python :: 3.12
Classifier: Topic :: Text Processing :: Linguistic
Classifier: Topic :: Software Development :: Libraries :: Python Modules
Classifier: Topic :: Scientific/Engineering :: Artificial Intelligence
Requires-Python: >=3.7
License-File: LICENSE
Provides-Extra: ml
Requires-Dist: sentence-transformers>=2.2.0; extra == "ml"
Provides-Extra: dev
Requires-Dist: build>=0.8.0; extra == "dev"
Requires-Dist: twine>=4.0.0; extra == "dev"
Requires-Dist: pytest>=7.0.0; extra == "dev"
Requires-Dist: pytest-cov>=3.0.0; extra == "dev"
Provides-Extra: test
Requires-Dist: pytest>=7.0.0; extra == "test"
Requires-Dist: pytest-cov>=3.0.0; extra == "test"
Provides-Extra: all
Requires-Dist: sentence-transformers>=2.2.0; extra == "all"
Provides-Extra: full
Requires-Dist: sentence-transformers>=2.2.0; extra == "full"
Requires-Dist: build>=0.8.0; extra == "full"
Requires-Dist: twine>=4.0.0; extra == "full"
Requires-Dist: pytest>=7.0.0; extra == "full"
Requires-Dist: pytest-cov>=3.0.0; extra == "full"
Provides-Extra: sentence-transformers
Requires-Dist: sentence-transformers>=2.2.0; extra == "sentence-transformers"
Dynamic: license-file
